mostlyai/sdk/__init__.py
mostlyai/sdk/domain.py
mostlyai/sdk/py.typed
mostlyai/sdk/_data/__init__.py
mostlyai/sdk/_data/auto_detect.py
mostlyai/sdk/_data/base.py
mostlyai/sdk/_data/context.py
mostlyai/sdk/_data/conversions.py
mostlyai/sdk/_data/dtype.py
mostlyai/sdk/_data/exceptions.py
mostlyai/sdk/_data/language_model.py
mostlyai/sdk/_data/metadata_objects.py
mostlyai/sdk/_data/non_context.py
mostlyai/sdk/_data/progress_callback.py
mostlyai/sdk/_data/pull.py
mostlyai/sdk/_data/pull_context.py
mostlyai/sdk/_data/pull_utils.py
mostlyai/sdk/_data/push.py
mostlyai/sdk/_data/constraints/transformations.py
mostlyai/sdk/_data/constraints/types/__init__.py
mostlyai/sdk/_data/constraints/types/base.py
mostlyai/sdk/_data/constraints/types/fixed_combinations.py
mostlyai/sdk/_data/constraints/types/inequality.py
mostlyai/sdk/_data/db/__init__.py
mostlyai/sdk/_data/db/base.py
mostlyai/sdk/_data/db/bigquery.py
mostlyai/sdk/_data/db/databricks.py
mostlyai/sdk/_data/db/hive.py
mostlyai/sdk/_data/db/mssql.py
mostlyai/sdk/_data/db/mysql.py
mostlyai/sdk/_data/db/oracle.py
mostlyai/sdk/_data/db/postgresql.py
mostlyai/sdk/_data/db/redshift.py
mostlyai/sdk/_data/db/snowflake.py
mostlyai/sdk/_data/db/sqlite.py
mostlyai/sdk/_data/db/types_coercion.py
mostlyai/sdk/_data/file/__init__.py
mostlyai/sdk/_data/file/base.py
mostlyai/sdk/_data/file/utils.py
mostlyai/sdk/_data/file/container/__init__.py
mostlyai/sdk/_data/file/container/aws.py
mostlyai/sdk/_data/file/container/azure.py
mostlyai/sdk/_data/file/container/bucket_based.py
mostlyai/sdk/_data/file/container/gcs.py
mostlyai/sdk/_data/file/container/minio.py
mostlyai/sdk/_data/file/table/__init__.py
mostlyai/sdk/_data/file/table/csv.py
mostlyai/sdk/_data/file/table/feather.py
mostlyai/sdk/_data/file/table/json.py
mostlyai/sdk/_data/file/table/parquet.py
mostlyai/sdk/_data/util/__init__.py
mostlyai/sdk/_data/util/common.py
mostlyai/sdk/_data/util/kerberos.py
mostlyai/sdk/_local/__init__.py
mostlyai/sdk/_local/cli.py
mostlyai-5.10.1.dist-info/METADATA
mostlyai-5.10.1.dist-info/WHEEL
mostlyai-5.10.1.dist-info/licenses/LICENSE
mostlyai-5.10.1.dist-info/RECORD
