Metadata-Version: 2.4
Name: mostlyai
Version: 5.10.1
Summary: Synthetic Data SDK
Project-URL: homepage, https://app.mostly.ai/
Project-URL: repository, https://github.com/mostly-ai/mostlyai
Project-URL: documentation, https://mostly-ai.github.io/mostlyai/
Author-email: MOSTLY AI <dev@mostly.ai>
License-Expression: Apache-2.0
License-File: LICENSE
Classifier: Development Status :: 5 - Production/Stable
Classifier: Intended Audience :: Developers
Classifier: Intended Audience :: Financial and Insurance Industry
Classifier: Intended Audience :: Healthcare Industry
Classifier: Intended Audience :: Information Technology
Classifier: Intended Audience :: Science/Research
Classifier: Intended Audience :: Telecommunications Industry
Classifier: License :: OSI Approved :: Apache Software License
Classifier: Operating System :: OS Independent
Classifier: Programming Language :: Python :: 3.10
Classifier: Programming Language :: Python :: 3.11
Classifier: Programming Language :: Python :: 3.12
Classifier: Programming Language :: Python :: 3.13
Classifier: Topic :: Software Development :: Libraries
Classifier: Typing :: Typed
Requires-Python: <3.14,>=3.10
Requires-Dist: duckdb>=1.2.1
Requires-Dist: environs>=9.5.0
Requires-Dist: greenlet>=3.1.1
Requires-Dist: gunicorn>=23.0.0
Requires-Dist: httpx>=0.25.0
Requires-Dist: ipywidgets>=8.1.0
Requires-Dist: pandas>=2.0.0
Requires-Dist: pathvalidate>=3.3.1
Requires-Dist: psutil>=5.9.5
Requires-Dist: pyarrow>=16.0.0
Requires-Dist: pycryptodomex>=3.10.0
Requires-Dist: pydantic<3,>=2.4.2
Requires-Dist: requests>=2.31.0
Requires-Dist: rich>=13.7.0
Requires-Dist: schema>=0.7.5
Requires-Dist: semantic-version>=2.10.0
Requires-Dist: smart-open>=6.0.0
Requires-Dist: sqlparse>=0.5.3
Requires-Dist: typer>=0.9.0
Requires-Dist: xxhash>=3.2.0
Provides-Extra: databricks
Requires-Dist: databricks-sql-connector<4,>=3.2.0; extra == 'databricks'
Provides-Extra: googlebigquery
Requires-Dist: sqlalchemy-bigquery<2,>=1.6.1; extra == 'googlebigquery'
Provides-Extra: hive
Requires-Dist: impyla<0.20,>=0.19.0; extra == 'hive'
Requires-Dist: kerberos<2,>=1.3.1; extra == 'hive'
Requires-Dist: pyhive[hive-pure-sasl]<0.8,>=0.7.0; extra == 'hive'
Provides-Extra: local
Requires-Dist: adlfs>=2023.4.0; extra == 'local'
Requires-Dist: azure-storage-blob>=12.16.0; extra == 'local'
Requires-Dist: cloudpathlib[azure,gs,s3]>=0.17.0; extra == 'local'
Requires-Dist: fastapi<0.125,>=0.116.0; extra == 'local'
Requires-Dist: filelock>=3.16.1; extra == 'local'
Requires-Dist: gcsfs>=2023.1.0; extra == 'local'
Requires-Dist: joblib>=1.4.2; extra == 'local'
Requires-Dist: mostlyai-engine==2.4.0; extra == 'local'
Requires-Dist: mostlyai-qa==1.9.8; extra == 'local'
Requires-Dist: networkx<4,>=3.0; extra == 'local'
Requires-Dist: openpyxl>=3.1.5; extra == 'local'
Requires-Dist: python-multipart>=0.0.20; extra == 'local'
Requires-Dist: s3fs>=2023.1.0; extra == 'local'
Requires-Dist: smart-open[azure,gcs,s3]>=6.3.0; extra == 'local'
Requires-Dist: sqlalchemy>=2.0.0; extra == 'local'
Requires-Dist: sshtunnel<0.5,>=0.4.0; extra == 'local'
Requires-Dist: torch<2.10.0,>=2.9.0; extra == 'local'
Requires-Dist: torchaudio<2.10.0,>=2.9.0; extra == 'local'
Requires-Dist: torchvision<0.25.0,>=0.24.0; extra == 'local'
Requires-Dist: uvicorn>=0.34.0; extra == 'local'
Requires-Dist: xlsxwriter<4,>=3.1.9; extra == 'local'
Provides-Extra: local-gpu
Requires-Dist: adlfs>=2023.4.0; extra == 'local-gpu'
Requires-Dist: azure-storage-blob>=12.16.0; extra == 'local-gpu'
Requires-Dist: cloudpathlib[azure,gs,s3]>=0.17.0; extra == 'local-gpu'
Requires-Dist: fastapi<0.125,>=0.116.0; extra == 'local-gpu'
Requires-Dist: filelock>=3.16.1; extra == 'local-gpu'
Requires-Dist: gcsfs>=2023.1.0; extra == 'local-gpu'
Requires-Dist: joblib>=1.4.2; extra == 'local-gpu'
Requires-Dist: mostlyai-engine[gpu]==2.4.0; extra == 'local-gpu'
Requires-Dist: mostlyai-qa==1.9.8; extra == 'local-gpu'
Requires-Dist: networkx<4,>=3.0; extra == 'local-gpu'
Requires-Dist: openpyxl>=3.1.5; extra == 'local-gpu'
Requires-Dist: python-multipart>=0.0.20; extra == 'local-gpu'
Requires-Dist: s3fs>=2023.1.0; extra == 'local-gpu'
Requires-Dist: smart-open[azure,gcs,s3]>=6.3.0; extra == 'local-gpu'
Requires-Dist: sqlalchemy>=2.0.0; extra == 'local-gpu'
Requires-Dist: sshtunnel<0.5,>=0.4.0; extra == 'local-gpu'
Requires-Dist: torch<2.10.0,>=2.9.0; extra == 'local-gpu'
Requires-Dist: torchaudio<2.10.0,>=2.9.0; extra == 'local-gpu'
Requires-Dist: torchvision<0.25.0,>=0.24.0; extra == 'local-gpu'
Requires-Dist: uvicorn>=0.34.0; extra == 'local-gpu'
Requires-Dist: xlsxwriter<4,>=3.1.9; extra == 'local-gpu'
Provides-Extra: mssql
Requires-Dist: pyodbc<6,>=5.1.0; extra == 'mssql'
Provides-Extra: mysql
Requires-Dist: mysql-connector-python<10,>=9.1.0; extra == 'mysql'
Provides-Extra: oracle
Requires-Dist: oracledb<3,>=2.2.1; extra == 'oracle'
Provides-Extra: postgres
Requires-Dist: psycopg2<3,>=2.9.4; extra == 'postgres'
Provides-Extra: redshift
Requires-Dist: redshift-connector>=2.1.8; extra == 'redshift'
Provides-Extra: snowflake
Requires-Dist: snowflake-sqlalchemy<2,>=1.6.1; extra == 'snowflake'
